trilateration/__init__.py
trilateration/cli.py
trilateration/solver.py
trilateration_coordfinder-1.0.4.dist-info/licenses/LICENSE
trilateration_coordfinder-1.0.4.dist-info/METADATA
trilateration_coordfinder-1.0.4.dist-info/WHEEL
trilateration_coordfinder-1.0.4.dist-info/entry_points.txt
trilateration_coordfinder-1.0.4.dist-info/top_level.txt
trilateration_coordfinder-1.0.4.dist-info/RECORD
