Metadata-Version: 2.4
Name: trilateration-coordfinder
Version: 1.0.4
Summary: High-precision geospatial trilateration solver using multiple optimization methods
Author-email: LOKAI7 <klima.luki@gmail.com>
Project-URL: Homepage, https://github.com/LOKAI7/trilateration-coordfinder
Project-URL: Bug Tracker, https://github.com/LOKAI77/trilateration-coordfinder/issues
Project-URL: Documentation, https://github.com/LOKAI77/trilateration-coordfinder#readme
Keywords: trilateration,geospatial,coordinates,optimization,gps,positioning
Classifier: Development Status :: 4 - Beta
Classifier: Intended Audience :: Science/Research
Classifier: Intended Audience :: Developers
Classifier: License :: OSI Approved :: MIT License
Classifier: Programming Language :: Python :: 3
Classifier: Programming Language :: Python :: 3.7
Classifier: Programming Language :: Python :: 3.8
Classifier: Programming Language :: Python :: 3.9
Classifier: Programming Language :: Python :: 3.10
Classifier: Programming Language :: Python :: 3.11
Classifier: Programming Language :: Python :: 3.12
Classifier: Topic :: Scientific/Engineering :: GIS
Classifier: Topic :: Scientific/Engineering :: Mathematics
Requires-Python: >=3.7
License-File: LICENSE
Requires-Dist: numpy>=1.21.0
Requires-Dist: scipy>=1.7.0
Requires-Dist: geopy>=2.2.0
Provides-Extra: dev
Requires-Dist: pytest>=7.0.0; extra == "dev"
Requires-Dist: black>=22.0.0; extra == "dev"
Requires-Dist: flake8>=4.0.0; extra == "dev"
Dynamic: license-file
